askoclics/__init__.py
askoclics/askolib/__init__.py
askoclics/askolib/client.py
askoclics/askolib/exceptions.py
askoclics/askolib/dataset/__init__.py
askoclics/askolib/file/__init__.py
askoclics/askolib/result/__init__.py
askoclics/askolib/sparql/__init__.py
askoclics/cli/__init__.py
askoclics/cli/cli.py
askoclics/cli/config.py
askoclics/cli/decorators.py
askoclics/cli/io.py
askoclics/cli/commands/__init__.py
askoclics/cli/commands/cmd_dataset.py
askoclics/cli/commands/cmd_file.py
askoclics/cli/commands/cmd_init.py
askoclics/cli/commands/cmd_result.py
askoclics/cli/commands/cmd_sparql.py
askoclics/cli/commands/dataset/__init__.py
askoclics/cli/commands/dataset/delete.py
askoclics/cli/commands/dataset/list.py
askoclics/cli/commands/dataset/set_private.py
askoclics/cli/commands/dataset/set_public.py
askoclics/cli/commands/file/__init__.py
askoclics/cli/commands/file/delete.py
askoclics/cli/commands/file/describe.py
askoclics/cli/commands/file/integrate_bed.py
askoclics/cli/commands/file/integrate_csv.py
askoclics/cli/commands/file/integrate_gff.py
askoclics/cli/commands/file/integrate_rdf.py
askoclics/cli/commands/file/list.py
askoclics/cli/commands/file/preview.py
askoclics/cli/commands/file/upload.py
askoclics/cli/commands/result/__init__.py
askoclics/cli/commands/result/delete.py
askoclics/cli/commands/result/download.py
askoclics/cli/commands/result/get_sparql.py
askoclics/cli/commands/result/list.py
askoclics/cli/commands/result/preview.py
askoclics/cli/commands/sparql/__init__.py
askoclics/cli/commands/sparql/info.py
askoclics/cli/commands/sparql/query.py
askoclics/cli/commands/sparql/template.py
askoclics-0.0.8.dist-info/LICENSE
askoclics-0.0.8.dist-info/METADATA
askoclics-0.0.8.dist-info/WHEEL
askoclics-0.0.8.dist-info/entry_points.txt
askoclics-0.0.8.dist-info/top_level.txt
askoclics-0.0.8.dist-info/RECORD
