Metadata-Version: 2.2
Name: askoclics
Version: 0.0.8
Summary: Askomics CLI
Home-page: https://github.com/mboudet/askoclics
Author: Mateo Boudet
Author-email: mateo.boudet@inrae.fr
License: MIT
Platform: Posix; MacOS X; Windows
Classifier: Intended Audience :: Developers
Classifier: License :: OSI Approved :: MIT License
Classifier: Operating System :: OS Independent
Classifier: Topic :: Scientific/Engineering
Classifier: Programming Language :: Python :: 3.7
License-File: LICENSE
Requires-Dist: wrapt
Requires-Dist: click
Requires-Dist: future
Requires-Dist: requests
Requires-Dist: pyyaml
Dynamic: author
Dynamic: author-email
Dynamic: classifier
Dynamic: description-content-type
Dynamic: home-page
Dynamic: license
Dynamic: platform
Dynamic: requires-dist
Dynamic: summary
